{"is_source_file": true, "format": "JavaScript", "description": "This file defines a client-side API wrapper for a web application, utilizing axios to communicate with a backend API. It sets up configuration for base URL, feature flags, and provides functions to perform health checks, manage products, alerts, and price history data, including create, fetch, and delete operations.", "external_files": ["axios"], "external_methods": ["axios.create", "axios.get", "axios.post", "axios.delete", "instance.interceptors.response.use"], "published": ["createApiClient", "healthcheck", "fetchProducts", "addProduct", "fetchAlerts", "fetchPriceHistory", "deleteProduct", "featureFlags"], "classes": [], "methods": [{"name": "parseFeatureFlags()", "description": "Parses feature flags from environment variables with fallback to default object.", "scope": "", "scopeKind": ""}, {"name": "addProduct(payload)", "scope": "", "scopeKind": "", "description": "unavailable"}, {"name": "createApiClient()", "scope": "", "scopeKind": "", "description": "unavailable"}, {"name": "deleteProduct(productId)", "scope": "", "scopeKind": "", "description": "unavailable"}, {"name": "fetchAlerts()", "scope": "", "scopeKind": "", "description": "unavailable"}, {"name": "fetchPriceHistory(productId)", "scope": "", "scopeKind": "", "description": "unavailable"}, {"name": "fetchProducts(query = \"\")", "scope": "", "scopeKind": "", "description": "unavailable"}, {"name": "healthcheck()", "scope": "", "scopeKind": "", "description": "unavailable"}], "calls": ["axios.create", "axios.get", "axios.post", "axios.delete", "JSON.parse", "Promise.reject"], "search-terms": ["client.js", "API_BASE", "featureFlags", "createApiClient", "healthcheck", "fetchProducts", "addProduct", "fetchAlerts", "fetchPriceHistory", "deleteProduct", "axios", "response interceptor"], "state": 2, "file_id": 13, "knowledge_revision": 57, "git_revision": "eeee9f6318e67265e8dce857251b1d6172efd771", "revision_history": [{"28": ""}, {"45": "47e2c7c25b0bfc8d99d4596156dae06217b44245"}, {"50": "75528902650784893466e7f2b16c4586d5d99bf5"}, {"57": "eeee9f6318e67265e8dce857251b1d6172efd771"}], "ctags": [{"_type": "tag", "name": "API_BASE", "path": "/home/kavia/workspace/code-generation/pricesense-web-application-45425-45429/frontend_react_js/src/api/client.js", "pattern": "/^const API_BASE =$/", "language": "JavaScript", "kind": "constant"}, {"_type": "tag", "name": "addProduct", "path": "/home/kavia/workspace/code-generation/pricesense-web-application-45425-45429/frontend_react_js/src/api/client.js", "pattern": "/^export async function addProduct(payload) {$/", "language": "JavaScript", "kind": "function", "signature": "(payload)"}, {"_type": "tag", "name": "createApiClient", "path": "/home/kavia/workspace/code-generation/pricesense-web-application-45425-45429/frontend_react_js/src/api/client.js", "pattern": "/^export function createApiClient() {$/", "language": "JavaScript", "kind": "function", "signature": "()"}, {"_type": "tag", "name": "deleteProduct", "path": "/home/kavia/workspace/code-generation/pricesense-web-application-45425-45429/frontend_react_js/src/api/client.js", "pattern": "/^export async function deleteProduct(productId) {$/", "language": "JavaScript", "kind": "function", "signature": "(productId)"}, {"_type": "tag", "name": "fetchAlerts", "path": "/home/kavia/workspace/code-generation/pricesense-web-application-45425-45429/frontend_react_js/src/api/client.js", "pattern": "/^export async function fetchAlerts() {$/", "language": "JavaScript", "kind": "function", "signature": "()"}, {"_type": "tag", "name": "fetchPriceHistory", "path": "/home/kavia/workspace/code-generation/pricesense-web-application-45425-45429/frontend_react_js/src/api/client.js", "pattern": "/^export async function fetchPriceHistory(productId) {$/", "language": "JavaScript", "kind": "function", "signature": "(productId)"}, {"_type": "tag", "name": "fetchProducts", "path": "/home/kavia/workspace/code-generation/pricesense-web-application-45425-45429/frontend_react_js/src/api/client.js", "pattern": "/^export async function fetchProducts(query = \"\") {$/", "language": "JavaScript", "kind": "function", "signature": "(query = \"\")"}, {"_type": "tag", "name": "healthcheck", "path": "/home/kavia/workspace/code-generation/pricesense-web-application-45425-45429/frontend_react_js/src/api/client.js", "pattern": "/^export async function healthcheck() {$/", "language": "JavaScript", "kind": "function", "signature": "()"}, {"_type": "tag", "name": "parseFeatureFlags", "path": "/home/kavia/workspace/code-generation/pricesense-web-application-45425-45429/frontend_react_js/src/api/client.js", "pattern": "/^function parseFeatureFlags() {$/", "language": "JavaScript", "kind": "function", "signature": "()"}], "hash": "6ca944fae1e01eb8d323fc8cb7598bc4", "format-version": 4, "code-base-name": "frontend_react_js", "filename": "frontend_react_js/src/api/client.js"}